{"dependencies":[{"name":"./scss/main.scss","dynamic":true},{"name":"./js/index.js","dynamic":true}],"generated":{"html":"<!DOCTYPE html>\n<html lang=\"en\">\n\n<head>\n    <meta charset=\"UTF-8\">\n    <meta name=\"viewport\" content=\"width=device-width, initial-scale=1.0\">\n    <meta http-equiv=\"X-UA-Compatible\" content=\"ie=edge\">\n\t\t<title>Personal Portfolio</title>\n\t\t<link href=\"https://fonts.googleapis.com/css?family=Barlow+Condensed:300,400,500,600,700\" rel=\"stylesheet\"> \n\t\t<link rel=\"stylesheet\" href=\"https://cdnjs.cloudflare.com/ajax/libs/font-awesome/4.7.0/css/font-awesome.css\">\n\t\t<link rel=\"stylesheet\" href=\"/dist/96efa2f3d0661d0c2e0868c8284cabae.css\">\n</head>\n\n<body class=\"work\">\n\t<div class=\"menu-icon\">\n\t\t\t<i class=\"fa fa-bars\" aria-hidden=\"true\"></i>\n\t</div>\n\t<section id=\"menu\">\n\t\t<nav>\n\t\t\t<a href=\"#\">Home</a>\n\t\t\t<a href=\"#\">About</a>\n\t\t\t<a href=\"#\">Portfolio</a>\n\t\t\t<a href=\"#\">Contact</a>\n\t\t</nav>\n\t</section>\n    <section class=\"info-section\">\n        <div class=\"logo\">\n\t\t\t\t\tAK\n\t\t\t\t</div>\n        <div class=\"info-box\">\n            <h4>Email</h4>\n            <p>hello@admirkurtovic.com</p>\n            <h4>Phone</h4>\n            <p>061 465 729</p>\n            <h4>Find me on</h4>\n            <div class=\"icon-section\">\n\t\t\t\t\t\t\t<a href=\"#\"><i class=\"fa fa-linkedin-square\" aria-hidden=\"true\"></i></a>\t\n\t\t\t\t\t\t\t<a href=\"#\"><i class=\"fa fa-twitter-square\" aria-hidden=\"true\"></i></a>\t\n\t\t\t\t\t\t\t<a href=\"#\"><i class=\"fa fa-instagram\" aria-hidden=\"true\"></i></a>\t\n\t\t\t\t\t\t\t<a href=\"#\"><i class=\"fa fa-free-code-camp\" aria-hidden=\"true\"></i></a>\t\n\t\t\t\t\t\t</div>\n\t\t\t\t\t</div>\n\t\t\t  </section>\n        <section class=\"content-area\">\n          <div class=\"scroll-section\">\n          <!-- work starts-->\n            <div class=\"work-section\">\n              <div class=\"title\">\n                  <h1>Latest Works</h1>\n                </div>\n                <div class=\"project-section\">\n                  <div class=\"project-box\" style=\"background: \n                  url('https://cdn.dribbble.com/users/188162/screenshots/2329965/nike_90.jpg') no-repeat center center;\">\n                    <div class=\"grey-bg\">\n                      <div class=\"project-info\">\n                        <div class=\"project-details\">\n                          Client : Nike Year: 2018  Type: Ecommerce\n                        </div>\n                        <div class=\"project-title\">\n                            The Last Yeezys\n                        </div>\n                        <div>\n                         <i class=\"fa fa-long-arrow-right\" aria-hidden=\"true\"></i>\n                        </div>  \n                      </div>  \n                    </div>\n                  </div>  \n                  <div class=\"project-box\" style=\"background: \n                  url('https://cdn.dribbble.com/users/443226/screenshots/4089537/pixel_studio.jpg') no-repeat center center;\">\n                    <div class=\"grey-bg\">\n                      <div class=\"project-info\">\n                        <div class=\"project-details\">\n                          Client : Nike Year: 2018  Type: Ecommerce\n                        </div>\n                        <div class=\"project-title\">\n                            The Last Yeezys\n                        </div>\n                        <div>\n                         <i class=\"fa fa-long-arrow-right\" aria-hidden=\"true\"></i>\n                        </div>  \n                      </div>  \n                    </div>\n                  </div>  \n                  <div class=\"project-box\" style=\"background: \n                  url('https://cdn.dribbble.com/users/443226/screenshots/4130898/iphone_x_mail_apps_design_exploration.jpg') no-repeat center center;\">\n                    <div class=\"grey-bg\">\n                      <div class=\"project-info\">\n                        <div class=\"project-details\">\n                          Client : Nike Year: 2018  Type: Ecommerce\n                        </div>\n                        <div class=\"project-title\">\n                            The Last Yeezys\n                        </div>\n                        <div>\n                         <i class=\"fa fa-long-arrow-right\" aria-hidden=\"true\"></i>\n                        </div>  \n                      </div>  \n                    </div>\n                  </div>  \n                  <div class=\"project-box\" style=\"background: \n                  url('https://cdn.dribbble.com/users/402092/screenshots/4152480/preview_dribbble_jetpress.jpg') no-repeat center center;\">\n                    <div class=\"grey-bg\">\n                      <div class=\"project-info\">\n                        <div class=\"project-details\">\n                          Client : Nike Year: 2018  Type: Ecommerce\n                        </div>\n                        <div class=\"project-title\">\n                            The Last Yeezys\n                        </div>\n                        <div>\n                         <i class=\"fa fa-long-arrow-right\" aria-hidden=\"true\"></i>\n                        </div>  \n                      </div>  \n                    </div>\n                  </div>  \n               </div>  \n         <!-- Work Ends -->\n      </div></div></section>\n    \n\n    <script type=\"text/javascript\" src=\"/dist/c62ab41a60be1ab0cabd8a900a3df611.js\"></script>\n</body>\n\n</html>"},"hash":"42c3f6a859444d0181248906d88c8bf1"}